{
  "id": "input.askConfirm",
  "category": "input",
  "categoryLabel": "Input Prompts",
  "icon": "pencil-square",
  "color": "var(--sol-orange)",
  "label": "Ask for Confirmation",
  "desc": "Show a yes/no confirmation dialog. Stores boolean.",
  "version": "1.0.0",
  "params": [
    {
      "name": "message",
      "label": "Message",
      "type": "text",
      "placeholder": "Are you sure?"
    },
    {
      "name": "into",
      "label": "Store in var",
      "type": "text",
      "placeholder": "confirmed"
    }
  ]
}
